README.md
setup.cfg
setup.py
pymization/__init__.py
pymization/algorithms.py
pymization/cds.py
pymization/solver.py
pymization.egg-info/PKG-INFO
pymization.egg-info/SOURCES.txt
pymization.egg-info/dependency_links.txt
pymization.egg-info/requires.txt
pymization.egg-info/top_level.txt