Metadata-Version: 2.1
Name: pymization
Version: 0.1.1
Summary: A simple optimization solverp problem
Home-page: https://github.com/mauricepoirrier/pymization
Author: Nicolas Camus & Maurice Poirrier
Author-email: maurice@merkenlabs.com
License: MIT
Download-URL: https://github.com/mauricepoirrier/pymization/archive/0.0.1.tar.gz
Platform: UNKNOWN
Classifier: Programming Language :: Python :: 3
Classifier: License :: OSI Approved :: MIT License
Classifier: Operating System :: OS Independent
